theticketbot/README.md
theticketbot/__init__.py
theticketbot/__main__.py
theticketbot/appdirs.py
theticketbot/bot.py
theticketbot/cogs/README.md
theticketbot/cogs/__init__.py
theticketbot/cogs/cleanup.py
theticketbot/cogs/errors.py
theticketbot/cogs/inbox/__init__.py
theticketbot/cogs/inbox/cog_group.py
theticketbot/cogs/inbox/cog_listeners.py
theticketbot/cogs/inbox/constants.py
theticketbot/cogs/inbox/destination.py
theticketbot/cogs/inbox/modals.py
theticketbot/cogs/inbox/ratelimits.py
theticketbot/cogs/inbox/staff.py
theticketbot/cogs/inbox/views.py
theticketbot/cogs/owner.py
theticketbot/cogs/select.py
theticketbot/config.py
theticketbot/config_default.toml
theticketbot/database.py
theticketbot/errors.py
theticketbot/locales/de/theticketbot.ftl
theticketbot/locales/en_US/theticketbot.ftl
theticketbot/locales/fr/theticketbot.ftl
theticketbot/logging.py
theticketbot/migrations/001-base.sql
theticketbot/migrations/002-add-default-ticket-name.sql
theticketbot/migrations/003-add-inbox-counter.sql
theticketbot/migrations/004-replace-name-placeholder.sql
theticketbot/migrations/005-add-inbox-destination.sql
theticketbot/migrations/006-add-setting-table.sql
theticketbot/migrations/007-index-cascading-columns.sql
theticketbot/migrations.py
theticketbot/py.typed
theticketbot/translator.py
theticketbot/versions.py
theticketbot/views.py
theticketbot-1.0.0.dist-info/licenses/LICENSE
theticketbot-1.0.0.dist-info/WHEEL
theticketbot-1.0.0.dist-info/entry_points.txt
theticketbot-1.0.0.dist-info/METADATA
theticketbot-1.0.0.dist-info/RECORD
