Metadata-Version: 2.4
Name: theticketbot
Version: 1.0.0
Summary: A simple Discord ticket bot built on private channel threads.
Keywords: i18n,discord,discord.py,project-fluent,ticketing-system
Author: thegamecracks
License-Expression: MIT
License-File: LICENSE
Classifier: Development Status :: 5 - Production/Stable
Classifier: Intended Audience :: End Users/Desktop
Classifier: License :: OSI Approved
Classifier: License :: OSI Approved :: MIT License
Classifier: Programming Language :: Python
Classifier: Programming Language :: Python :: 3
Classifier: Programming Language :: Python :: 3.11
Classifier: Programming Language :: Python :: 3.12
Classifier: Programming Language :: Python :: 3.13
Classifier: Programming Language :: Python :: 3.14
Classifier: Topic :: Communications :: Chat
Classifier: Typing :: Typed
Requires-Dist: asqlite~=2.0
Requires-Dist: discord-py~=2.6
Requires-Dist: fluent-compiler~=1.1
Requires-Dist: humanize~=4.15
Requires-Dist: packaging~=25.0
Requires-Dist: platformdirs~=4.5
Requires-Dist: pydantic~=2.12
Requires-Dist: jishaku>=2.6.3 ; extra == 'jishaku'
Requires-Python: >=3.11
Project-URL: Changelog, https://github.com/thegamecracks/theticketbot/blob/main/CHANGELOG.md
Project-URL: Homepage, https://github.com/thegamecracks/theticketbot
Project-URL: Issues, https://github.com/thegamecracks/theticketbot/issues
Provides-Extra: jishaku
